doc/conf.py
doc/comparisons/pypit_vs_lowredux.py
doc/demos/LRISr_longslit.py
doc/scripts/build_afterburn_datamodels_rst.py
doc/scripts/build_bitmask_rst.py
doc/scripts/build_cache_data_tbl.py
doc/scripts/build_calib_images_rst.py
doc/scripts/build_datacontainer_datamodels.py
doc/scripts/build_dependency_rst.py
doc/scripts/build_detector_table.py
doc/scripts/build_imgproc_defaults.py
doc/scripts/build_par_rst.py
doc/scripts/build_specobj_rst.py
doc/scripts/build_spectbl_rst.py
doc/scripts/build_standardstbl_rst.py
doc/scripts/make_example_files.py
doc/scripts/unique_configuration_keys.py
doc/scripts/write_script_help.py
licenses/PYDL_LICENSE.rst
pypeit/__init__.py
pypeit/alignframe.py
pypeit/archive.py
pypeit/bitmask.py
pypeit/cache.py
pypeit/calibframe.py
pypeit/calibrations.py
pypeit/coadd1d.py
pypeit/coadd2d.py
pypeit/coadd3d.py
pypeit/datamodel.py
pypeit/edgetrace.py
pypeit/extraction.py
pypeit/find_objects.py
pypeit/flatfield.py
pypeit/fluxcalibrate.py
pypeit/history.py
pypeit/inputfiles.py
pypeit/io.py
pypeit/manual_extract.py
pypeit/metadata.py
pypeit/onespec.py
pypeit/orderstack.py
pypeit/pypeit.py
pypeit/pypeitdata.py
pypeit/pypeitsetup.py
pypeit/pypmsgs.py
pypeit/sampling.py
pypeit/scattlight.py
pypeit/sensfilearchive.py
pypeit/sensfunc.py
pypeit/slittrace.py
pypeit/spec2dobj.py
pypeit/specobj.py
pypeit/specobjs.py
pypeit/telescopes.py
pypeit/tracepca.py
pypeit/utils.py
pypeit/version.py
pypeit/wavecalib.py
pypeit/wavemodel.py
pypeit/wavetilts.py
pypeit/bspline/__init__.py
pypeit/bspline/bspline.py
pypeit/bspline/util.py
pypeit/core/__init__.py
pypeit/core/arc.py
pypeit/core/basis.py
pypeit/core/coadd.py
pypeit/core/collate.py
pypeit/core/combine.py
pypeit/core/convert_DEIMOSsavfiles.py
pypeit/core/datacube.py
pypeit/core/extract.py
pypeit/core/findobj_skymask.py
pypeit/core/fitting.py
pypeit/core/flat.py
pypeit/core/flexure.py
pypeit/core/flux_calib.py
pypeit/core/framematch.py
pypeit/core/meta.py
pypeit/core/moment.py
pypeit/core/mosaic.py
pypeit-1.18.1.dist-info/licenses/LICENSE.rst
pypeit-1.18.1.dist-info/METADATA
pypeit-1.18.1.dist-info/WHEEL
pypeit-1.18.1.dist-info/entry_points.txt
pypeit-1.18.1.dist-info/top_level.txt
pypeit-1.18.1.dist-info/RECORD
