Metadata-Version: 2.4
Name: pypeit
Version: 1.18.1
Summary: PypeIt Spectroscopic Reduction
Author-email: PypeIt Collaboration <pypeit@ucolick.org>
License: Copyright (c) 2018-2023, PypeIt Developers
Project-URL: Repository, https://github.com/pypeit/PypeIt
Project-URL: Documentation, https://pypeit.readthedocs.io/
Keywords: pypeit,PypeIt,astronomy,Keck,UCO,Lick,spectroscopy,data reduction
Classifier: Development Status :: 4 - Beta
Classifier: Intended Audience :: Science/Research
Classifier: Topic :: Scientific/Engineering :: Astronomy
Classifier: Topic :: Software Development :: Libraries :: Python Modules
Classifier: Topic :: Software Development :: User Interfaces
Classifier: Natural Language :: English
Classifier: Operating System :: OS Independent
Classifier: Programming Language :: Python
Classifier: Programming Language :: Python :: 3.11
Classifier: Programming Language :: Python :: 3.12
Classifier: Programming Language :: Python :: 3.13
Requires-Python: <3.14,>=3.11
License-File: LICENSE.rst
Requires-Dist: numpy>=2.0
Requires-Dist: astropy>=7.0
Requires-Dist: packaging>=22.0
Requires-Dist: scipy>=1.9
Requires-Dist: matplotlib>=3.7
Requires-Dist: PyYAML>=6.0
Requires-Dist: PyERFA>=2.0.0
Requires-Dist: fast-histogram>=0.11
Requires-Dist: configobj>=5.0.6
Requires-Dist: scikit-learn>=1.2
Requires-Dist: IPython>=8.0.0
Requires-Dist: ginga>=5.4.0
Requires-Dist: setuptools<81
Requires-Dist: linetools>=0.3.2
Requires-Dist: qtpy>=2.2.0
Requires-Dist: pygithub
Requires-Dist: bottleneck
Requires-Dist: pyqt6
Provides-Extra: scikit-image
Requires-Dist: scikit-image>=0.23; extra == "scikit-image"
Provides-Extra: specutils
Requires-Dist: specutils>=2.0; extra == "specutils"
Provides-Extra: test
Requires-Dist: pygit2; extra == "test"
Requires-Dist: pytest>=7.0.0; extra == "test"
Requires-Dist: pytest-astropy; extra == "test"
Requires-Dist: tox; extra == "test"
Requires-Dist: pytest-cov; extra == "test"
Requires-Dist: coverage; extra == "test"
Provides-Extra: docs
Requires-Dist: sphinx<8,>=1.6; extra == "docs"
Requires-Dist: docutils<0.22; extra == "docs"
Requires-Dist: sphinx-automodapi; extra == "docs"
Requires-Dist: sphinx-design; extra == "docs"
Requires-Dist: sphinx_rtd_theme==2.0.0; extra == "docs"
Provides-Extra: devsuite
Requires-Dist: psutil; extra == "devsuite"
Requires-Dist: pytest-qt; extra == "devsuite"
Provides-Extra: dev
Requires-Dist: scikit-image>=0.23; extra == "dev"
Requires-Dist: specutils>=2.0; extra == "dev"
Requires-Dist: pygit2; extra == "dev"
Requires-Dist: pytest>=7.0.0; extra == "dev"
Requires-Dist: pytest-astropy; extra == "dev"
Requires-Dist: tox; extra == "dev"
Requires-Dist: pytest-cov; extra == "dev"
Requires-Dist: coverage; extra == "dev"
Requires-Dist: sphinx<8,>=1.6; extra == "dev"
Requires-Dist: docutils<0.22; extra == "dev"
Requires-Dist: sphinx-automodapi; extra == "dev"
Requires-Dist: sphinx-design; extra == "dev"
Requires-Dist: sphinx_rtd_theme==2.0.0; extra == "dev"
Requires-Dist: psutil; extra == "dev"
Requires-Dist: pytest-qt; extra == "dev"
Dynamic: license-file
